mp42uni/__init__.py
mp42uni-1.0.5.dist-info/LICENSE
mp42uni-1.0.5.dist-info/METADATA
mp42uni-1.0.5.dist-info/WHEEL
mp42uni-1.0.5.dist-info/entry_points.txt
mp42uni-1.0.5.dist-info/top_level.txt
mp42uni-1.0.5.dist-info/RECORD
