Metadata-Version: 2.1
Name: mp42uni
Version: 1.0.5
Summary: Use this to show a video in the terminal (Unicode art)
Home-page: https://github.com/donno2048/mp42uni
Author: Elisha Hollander
License: MIT
Platform: UNKNOWN
Classifier: Programming Language :: Python :: 3
License-File: LICENSE
Requires-Dist: opencv-python (>=4.5.2.52)
Requires-Dist: Pillow (>=8.3.2)
Requires-Dist: questionary (>=1.10.0)
